blogger2zinnia-1.1.dist-info/metadata.json
blogger2zinnia-1.1.dist-info/METADATA
blogger2zinnia-1.1.dist-info/RECORD
blogger2zinnia-1.1.dist-info/WHEEL
blogger2zinnia-1.1.dist-info/DESCRIPTION.rst
blogger2zinnia-1.1.dist-info/top_level.txt
zinnia_blogger/__init__.py
zinnia_blogger/management/__init__.py
zinnia_blogger/management/commands/blogger2zinnia.py
zinnia_blogger/management/commands/__init__.py
